{
  "id": "skilltree:archer_13",
  "bonuses": [
    {
      "type": "skilltree:item_usage_speed",
      "multiplier": 0.02
    }
  ],
  "requirements": [],
  "directConnections": [
    "skilltree:archer_11",
    "skilltree:archer_16"
  ],
  "longConnections": [],
  "oneWayConnections": [],
  "tags": [],
  "backgroundTexture": "skilltree:textures/icons/background/lesser.png",
  "iconTexture": "artifacts:textures/item/vampiric_glove.png",
  "borderTexture": "skilltree:textures/tooltip/lesser.png",
  "title": "Utility",
  "positionX": 87.08,
  "positionY": -21.92,
  "buttonSize": 14,
  "isStartingPoint": false
}