{
  "id": "skilltree:archer_135",
  "bonuses": [
    {
      "type": "skilltree:attribute",
      "attribute": "obscure_api:accuracy",
      "id": "6abef980-1944-423d-b31f-4b8150bc9b9e",
      "name": "Skill",
      "amount": 0.1,
      "operation": 0
    }
  ],
  "requirements": [],
  "directConnections": [
    "skilltree:archer_133"
  ],
  "longConnections": [],
  "oneWayConnections": [
    "skilltree:archer_137"
  ],
  "tags": [],
  "backgroundTexture": "skilltree:textures/icons/background/lesser.png",
  "iconTexture": "goety:textures/item/void_eye.png",
  "borderTexture": "skilltree:textures/tooltip/lesser.png",
  "title": "Accuracy",
  "positionX": 253.127,
  "positionY": -175.161,
  "buttonSize": 14,
  "isStartingPoint": false,
  "description": [
    {
      "f_131101_": {
        "f_131257_": 8092645
      },
      "text": "+10% Accuracy"
    }
  ]
}