{
  "id": "skilltree:archer_19",
  "bonuses": [
    {
      "type": "skilltree:inflict_effect",
      "chance": 0.2,
      "max_stacks": 1,
      "effect": "goety:freezing",
      "duration": 40,
      "amplifier": 0,
      "event_listener": {
        "damage_condition": {
          "type": "skilltree:projectile"
        },
        "target": "enemy",
        "type": "skilltree:attack"
      }
    }
  ],
  "requirements": [],
  "directConnections": [
    "skilltree:archer_18"
  ],
  "longConnections": [],
  "oneWayConnections": [],
  "tags": [],
  "backgroundTexture": "skilltree:textures/icons/background/lesser.png",
  "iconTexture": "guildedarrows:textures/item/frost_arrow.png",
  "borderTexture": "skilltree:textures/tooltip/lesser.png",
  "title": "Debuff",
  "positionX": 213.0,
  "positionY": 0.0,
  "buttonSize": 14,
  "isStartingPoint": false
}